resilient_exporters/__init__.py
resilient_exporters/exceptions/__init__.py
resilient_exporters/exporters/__init__.py
resilient_exporters/exporters/exporter.py
resilient_exporters/exporters/exporter_elasticsearch.py
resilient_exporters/exporters/exporter_file.py
resilient_exporters/exporters/exporter_mongodb.py
resilient_exporters/exporters/exporter_pool.py
resilient_exporters/exporters/exporter_postgresql.py
resilient_exporters/exporters/exporter_sqlserver.py
resilient_exporters/utils.py
resilient_exporters-0.1.6.dist-info/LICENSE
resilient_exporters-0.1.6.dist-info/WHEEL
resilient_exporters-0.1.6.dist-info/METADATA
resilient_exporters-0.1.6.dist-info/RECORD
