Metadata-Version: 2.1
Name: resilient-exporters
Version: 0.1.6
Summary: A package to export data to databases resiliently.
Home-page: https://github.com/arbfay/resilient-exporters.git
License: MIT
Keywords: data-engineering,exporter,data,mongodb,elasticsearch,postgres
Author: Fayçal Arbai
Author-email: arbai.faycal@gmail.com
Requires-Python: >=3.6
Classifier: Development Status :: 2 - Pre-Alpha
Classifier: Intended Audience :: Developers
Classifier: Intended Audience :: Education
Classifier: Intended Audience :: Other Audience
Classifier: Intended Audience :: Science/Research
Classifier: License :: OSI Approved :: MIT License
Classifier: Operating System :: MacOS
Classifier: Operating System :: Microsoft :: Windows
Classifier: Operating System :: POSIX :: Linux
Classifier: Programming Language :: Python :: 3
Classifier: Programming Language :: Python :: 3.6
Classifier: Programming Language :: Python :: 3.7
Classifier: Programming Language :: Python :: 3.8
Classifier: Programming Language :: Python :: 3.9
Classifier: Topic :: Database
Classifier: Topic :: Home Automation
Classifier: Topic :: Software Development :: Libraries :: Python Modules
Classifier: Typing :: Typed
Provides-Extra: all
Provides-Extra: elastic
Provides-Extra: mongo
Provides-Extra: postgres
Requires-Dist: elasticsearch[async] (>6.0); extra == "all" or extra == "elastic"
Requires-Dist: orjson
Requires-Dist: psycopg2-binary (>=2.7,<3.0); extra == "all" or extra == "postgres"
Requires-Dist: pymongo (>=3,<4); extra == "all" or extra == "mongo"
Requires-Dist: requests
Project-URL: Documentation, https://resilient-exporters.readthedocs.io
Project-URL: Repository, https://github.com/arbfay/resilient-exporters.git
